llm_kit/__init__.py
llm_kit/llm_kit.py
llm_kit-0.1.0.dist-info/AUTHORS.rst
llm_kit-0.1.0.dist-info/LICENSE
llm_kit-0.1.0.dist-info/METADATA
llm_kit-0.1.0.dist-info/WHEEL
llm_kit-0.1.0.dist-info/top_level.txt
llm_kit-0.1.0.dist-info/RECORD
