Metadata-Version: 2.1
Name: llm-kit
Version: 0.1.0
Summary: A pythonic way to call llms & implement llm algorithms.
Home-page: https://github.com/smy20011/llm_kit
Author: Siyuan Ma
Author-email: smy20011@gmail.com
License: MIT license
Keywords: llm_kit
Classifier: Development Status :: 2 - Pre-Alpha
Classifier: Intended Audience :: Developers
Classifier: License :: OSI Approved :: MIT License
Classifier: Natural Language :: English
Classifier: Programming Language :: Python :: 3
Classifier: Programming Language :: Python :: 3.6
Classifier: Programming Language :: Python :: 3.7
Classifier: Programming Language :: Python :: 3.8
Requires-Python: >=3.6
License-File: LICENSE
License-File: AUTHORS.rst
